sqlite_help_functions/__init__.py
sqlite_help_functions/main.py
sqlite_help_functions/setup.py
this_is_my_package_called_password/my_password.py
this_is_my_package_called_password/setup.py
sqlite_help_functions-3.0.0.dist-info/METADATA
sqlite_help_functions-3.0.0.dist-info/WHEEL
sqlite_help_functions-3.0.0.dist-info/top_level.txt
sqlite_help_functions-3.0.0.dist-info/RECORD
